lbmpy_walberla/__init__.py
lbmpy_walberla/boundary.py
lbmpy_walberla/sparse.py
lbmpy_walberla/walberla_lbm_generation.py
lbmpy_walberla/templates/Boundary.tmpl.cpp
lbmpy_walberla/templates/Boundary.tmpl.h
lbmpy_walberla/templates/LatticeModel.tmpl.cpp
lbmpy_walberla/templates/LatticeModel.tmpl.h
lbmpy_walberla-0.2.8.dist-info/METADATA
lbmpy_walberla-0.2.8.dist-info/WHEEL
lbmpy_walberla-0.2.8.dist-info/top_level.txt
lbmpy_walberla-0.2.8.dist-info/RECORD
