Metadata-Version: 2.1
Name: lbmpy-walberla
Version: 0.2.8
Summary: Code Generation for Lattice Boltzmann Methods in the walberla framework
Home-page: https://i10git.cs.fau.de/pycodegen/lbmpy_walberla/
Author: Martin Bauer
Author-email: martin.bauer@fau.de
License: AGPLv3
Platform: UNKNOWN
Requires-Dist: lbmpy
Requires-Dist: pystencils-walberla
